AUTHORS
LICENSE
MANIFEST.in
README
finddata.pyc
setup.py
dist/django-sct-0.7/README
dist/django-sct-0.7/finddata.pyc
dist/django-sct-0.7/dist/files/README
dist/django-sct-0.7/django_sct.egg-info/SOURCES.txt
dist/django-sct-0.7/django_sct.egg-info/dependency_links.txt
dist/django-sct-0.7/django_sct.egg-info/requires.txt
dist/django-sct-0.7/django_sct.egg-info/top_level.txt
dist/django-sct-0.7/examples/buildout_project/sph_project/apps/sph_theme/locale/pl/LC_MESSAGES/django.mo
dist/django-sct-0.7/examples/buildout_project/sph_project/apps/sph_theme/locale/pl/LC_MESSAGES/django.po
dist/django-sct-0.7/examples/buildout_project/sph_project/apps/sph_theme/static/css/sph_theme.css
dist/django-sct-0.7/examples/buildout_project/sph_project/apps/sph_theme/templates/404.html
dist/django-sct-0.7/examples/buildout_project/sph_project/apps/sph_theme/templates/500.html
dist/django-sct-0.7/examples/buildout_project/sph_project/apps/sph_theme/templates/_below_navigation.html
dist/django-sct-0.7/examples/buildout_project/sph_project/apps/sph_theme/templates/_footer.html
dist/django-sct-0.7/examples/buildout_project/sph_project/apps/sph_theme/templates/_head.html
dist/django-sct-0.7/examples/buildout_project/sph_project/apps/sph_theme/templates/base.html
dist/django-sct-0.7/examples/buildout_project/sph_project/apps/sph_theme/templates/base_root.html
dist/django-sct-0.7/examples/buildout_project/sph_project/apps/sph_theme/templates/body.html
dist/django-sct-0.7/examples/buildout_project/sph_project/apps/sph_theme/templates/feeds/wiki_description.html
dist/django-sct-0.7/examples/buildout_project/sph_project/apps/sph_theme/templates/feeds/wiki_title.html
dist/django-sct-0.7/examples/buildout_project/sph_project/apps/sph_theme/templates/registration/logged_out.html
dist/django-sct-0.7/examples/buildout_project/sph_project/apps/sph_theme/templates/registration/login.html
dist/django-sct-0.7/examples/buildout_project/sph_project/apps/sph_theme/templates/wiki/news.html
dist/django-sct-0.7/examples/simpleproject/README
dist/django-sct-0.7/sphenecoll/sphene/__init__.pyc
dist/django-sct-0.7/sphenecoll/sphene/community/__init__.pyc
dist/django-sct-0.7/sphenecoll/sphene/community/admin.pyc
django_sct.egg-info/PKG-INFO
django_sct.egg-info/SOURCES.txt
django_sct.egg-info/dependency_links.txt
django_sct.egg-info/not-zip-safe
django_sct.egg-info/requires.txt
django_sct.egg-info/top_level.txt
